pulseapi/__init__.py
pulseapi/__main__.py
pulseapi/client.py
pulseapi/api/__init__.py
pulseapi/api/url_factory.py
pulseapi/structures/__init__.py
pulseapi/structures/pulse.py
pulseapi/structures/stats.py
pulseapi/structures/teams.py
pulseapi/structures/users.py
pulseapi-0.1.1.dist-info/LICENSE
pulseapi-0.1.1.dist-info/METADATA
pulseapi-0.1.1.dist-info/WHEEL
pulseapi-0.1.1.dist-info/top_level.txt
pulseapi-0.1.1.dist-info/RECORD
